benten/__init__.py
benten/__main__.py
benten/configuration.py
benten/version.py
benten/code/__init__.py
benten/code/document.py
benten/code/executioncontext.py
benten/code/intelligence.py
benten/code/intelligencecontext.py
benten/code/requirements.py
benten/code/sampledata.py
benten/code/schemadef.py
benten/code/symbols.py
benten/code/workflow.py
benten/code/workflowgraph.py
benten/code/yaml.py
benten/cwl/__init__.py
benten/cwl/alltypes.py
benten/cwl/anytype.py
benten/cwl/arraytype.py
benten/cwl/basetype.py
benten/cwl/enumtype.py
benten/cwl/expressiontype.py
benten/cwl/importincludetype.py
benten/cwl/lib.py
benten/cwl/linkedfiletype.py
benten/cwl/linkedschemadeftype.py
benten/cwl/lomtype.py
benten/cwl/namespacedtype.py
benten/cwl/recordtype.py
benten/cwl/requirementstype.py
benten/cwl/specification.py
benten/cwl/typeinference.py
benten/cwl/unknowntype.py
benten/langserver/__init__.py
benten/langserver/base.py
benten/langserver/completion.py
benten/langserver/definition.py
benten/langserver/documentsymbol.py
benten/langserver/fileoperation.py
benten/langserver/formatting.py
benten/langserver/hover.py
benten/langserver/jsonrpc.py
benten/langserver/lspobjects.py
benten/langserver/server.py
benten_schemas/__init__.py
benten_schemas/schema-v1.0.json
benten_schemas/schema-v1.1.json
benten_schemas/schema-v1.2.0-dev1.json
benten_schemas/schema-v1.2.0-dev3.json
benten_schemas/schema-v1.2.0.json
benten-2021.1.5.dist-info/LICENSE
benten-2021.1.5.dist-info/METADATA
benten-2021.1.5.dist-info/WHEEL
benten-2021.1.5.dist-info/entry_points.txt
benten-2021.1.5.dist-info/top_level.txt
benten-2021.1.5.dist-info/RECORD
