Metadata-Version: 2.1
Name: benten
Version: 2021.1.5
Summary: CWL language server developed by Seven Bridges
Home-page: https://github.com/rabix/benten
Author: Seven Bridges Genomics Inc.
Author-email: kaushik.ghose@sbgenomics.com
Maintainer: Seven Bridges Genomics Inc.
Maintainer-email: kaushik.ghose@sbgenomics.com
License: Copyright (c) 2021 Seven Bridges
Keywords: seven bridges cwl common workflow language
Platform: POSIX
Platform: MacOS
Platform: Windows
Classifier: Development Status :: 5 - Production/Stable
Classifier: Intended Audience :: Developers
Classifier: License :: OSI Approved :: Apache Software License
Classifier: Natural Language :: English
Classifier: Operating System :: POSIX
Classifier: Programming Language :: Python :: 3.7
Classifier: Programming Language :: Python :: 3 :: Only
Requires-Python: >=3.7.0
Requires-Dist: ruamel.yaml (==0.16.12)
Requires-Dist: dukpy (>=0.2.2)
Requires-Dist: cwlformat (>=2021.1.5)
